django_dj_plugin/__init__.py
django_dj_plugin/admin.py
django_dj_plugin/apps.py
django_dj_plugin/models.py
django_dj_plugin/urls.py
django_dj_plugin/utils.py
django_dj_plugin/views.py
django_dj_plugin/month/__init__.py
django_dj_plugin/month/forms.py
django_dj_plugin/month/models.py
django_dj_plugin/month/util.py
django_dj_plugin/month/widgets.py
django_dj_plugin/static/css/django_dj_plugin.css
django_dj_plugin/static/js/django_dj_plugin.js
django_dj_plugin/static/month/field/widget_month.css
django_dj_plugin/templates/django_dj_plugin/base.html
django_dj_plugin/test_utils/__init__.py
django_dj_plugin/test_utils/test_app/__init__.py
django_dj_plugin/test_utils/test_app/admin.py
django_dj_plugin/test_utils/test_app/apps.py
django_dj_plugin/test_utils/test_app/models.py
django_dj_plugin/test_utils/test_app/migrations/0001_initial.py
django_dj_plugin/test_utils/test_app/migrations/__init__.py
django_dj_plugin-0.3.0.dist-info/AUTHORS.rst
django_dj_plugin-0.3.0.dist-info/LICENSE
django_dj_plugin-0.3.0.dist-info/METADATA
django_dj_plugin-0.3.0.dist-info/WHEEL
django_dj_plugin-0.3.0.dist-info/top_level.txt
django_dj_plugin-0.3.0.dist-info/RECORD
