Metadata-Version: 2.1
Name: django-dj-plugin
Version: 0.3.0
Summary: Django plgooge practice modules.
Home-page: https://github.com/daimon99/django-dj-plugin
Author: Jian Dai
Author-email: daijian1@qq.com
License: MIT
Keywords: django-dj-plugin
Platform: UNKNOWN
Classifier: Development Status :: 3 - Alpha
Classifier: Framework :: Django :: 2.1
Classifier: Intended Audience :: Developers
Classifier: License :: OSI Approved :: BSD License
Classifier: Natural Language :: English
Classifier: Programming Language :: Python :: 2
Classifier: Programming Language :: Python :: 2.7
Classifier: Programming Language :: Python :: 3
Classifier: Programming Language :: Python :: 3.5
Classifier: Programming Language :: Python :: 3.6
